<?xml version="1.0" encoding="utf-8"?>
<Defs>
  <!--
    Better Traders Guild - Crew Quarters Comm Supplies Prefab

    Features:
    - 2x5 prefab size
    - Comms console for communications
    - Survival meal pallet for emergency supplies

    Design (top view, North is up):
        x: 0 1
    z=4:  [C] [C]     CommsConsole (3x2, defaultPlacingRot=South)
    z=3:  [C] [C]     relativeRotation=Clockwise rotates South->East = 2x3
    z=2:  [C] [C]     interactionCellOffset=(0,0,2) rotates to (+2,0,0) = East of console
    z=1:  [pallet]    Pallet_SurvivalMeals (2x2)
    z=0:  [pallet]

    Legend:
    C = CommsConsole (2x3 after rotation, bottom-left at x=0 z=2)
    pallet = Pallet_SurvivalMeals (2x2)

    Note: Interaction cell ends up 2 cells East (outside prefab), which is
    acceptable for a filler prefab - the adjacent area should be walkable.
  -->

  <PrefabDef>
    <defName>BTG_CrewQuartersCommSupplies2x5</defName>
    <size>(2,5)</size>

    <things>
      <CommsConsole>
        <position>(0, 0, 3)</position>
        <relativeRotation>Clockwise</relativeRotation>
      </CommsConsole>
      <Pallet_SurvivalMeals>
        <position>(0, 0, 0)</position>
      </Pallet_SurvivalMeals>
    </things>

  </PrefabDef>
</Defs>